fastjsonpy/__init__.py
fastjsonpy-1.1.dist-info/LICENSE
fastjsonpy-1.1.dist-info/METADATA
fastjsonpy-1.1.dist-info/WHEEL
fastjsonpy-1.1.dist-info/top_level.txt
fastjsonpy-1.1.dist-info/RECORD
