Metadata-Version: 2.1
Name: fastjsonpy
Version: 1.1
Summary: Fast Json makes Json faster
Author-email: Pimik <thepimik@gmail.com>
Project-URL: Homepage, https://github.com/the-mw-dev/fastjson
Project-URL: Issues, https://github.com/the-mw-dev/fastjson/issues
Classifier: Programming Language :: Python :: 3
Classifier: License :: OSI Approved :: MIT License
Classifier: Operating System :: OS Independent
Requires-Python: >=3.7
License-File: LICENSE
